CHANGELOG.md
bootloader/__init__.py
bootloader/unreal_engine/__init__.py
bootloader/unreal_engine/cli/__init__.py
bootloader/unreal_engine/cli/ueprjver.py
bootloader/unreal_engine/model/__init__.py
bootloader/unreal_engine/model/apple_version.py
bootloader/unreal_engine/utils/__init__.py
bootloader/unreal_engine/utils/project_version.py
ue_project_version-0.0.16.dist-info/entry_points.txt
ue_project_version-0.0.16.dist-info/LICENSE
ue_project_version-0.0.16.dist-info/WHEEL
ue_project_version-0.0.16.dist-info/METADATA
ue_project_version-0.0.16.dist-info/RECORD
